soulmoment/SoulMoment.cairo
soulmoment/__init__.py
soulmoment/library.cairo
soulmoment/account/SoulAccount.cairo
checksfinance_soulmoment-0.0.1.dist-info/LICENSE
checksfinance_soulmoment-0.0.1.dist-info/METADATA
checksfinance_soulmoment-0.0.1.dist-info/WHEEL
checksfinance_soulmoment-0.0.1.dist-info/top_level.txt
checksfinance_soulmoment-0.0.1.dist-info/RECORD
