Metadata-Version: 2.1
Name: checksfinance-soulmoment
Version: 0.0.1
Summary: An implementation of Soul-bound token in Cairo.
Home-page: https://github.com/ChecksFinance/soul-moment
Author: GUO Yu
Author-email: contact@checks.finance
License: MIT
Platform: any
Classifier: Operating System :: OS Independent
License-File: LICENSE
Requires-Dist: importlib-metadata (>=4.0)
Provides-Extra: testing
Requires-Dist: setuptools ; extra == 'testing'
Requires-Dist: tox ; extra == 'testing'
Requires-Dist: pytest ; extra == 'testing'
